{
  "project_info": {
    "project_number": "82849261108",
    "project_id": "react-native-task-force",
    "storage_bucket": "react-native-task-force.firebasestorage.app"
  },
  "client": [
    {
      "client_info": {
        "mobilesdk_app_id": "1:82849261108:android:a0efccf8d5b7c8b86b0c61",
        "android_client_info": {
          "package_name": "com.taskforce"
        }
      },
      "oauth_client": [],
      "api_key": [
        {
          "current_key": "AIzaSyBBpPdCV7oT_L4Os4bpZT84UDx0pHS3eEk"
        }
      ],
      "services": {
        "appinvite_service": {
          "other_platform_oauth_client": []
        }
      }
    }
  ],
  "configuration_version": "1"
}